bump_version/__init__.py
bump_version/_version.py
bump_version/cli.py
bump_version/py.typed
bump_version/version_manager.py
ai_app_base_bump_version-0.1.1.dist-info/METADATA
ai_app_base_bump_version-0.1.1.dist-info/WHEEL
ai_app_base_bump_version-0.1.1.dist-info/entry_points.txt
ai_app_base_bump_version-0.1.1.dist-info/licenses/LICENSE
ai_app_base_bump_version-0.1.1.dist-info/RECORD
