Metadata-Version: 2.4
Name: ai-app-base-bump-version
Version: 0.1.1
Summary: A CLI tool for semantic version management
Project-URL: Homepage, https://github.com/ai-app-base/bump-version-py
Project-URL: Repository, https://github.com/ai-app-base/bump-version-py.git
Project-URL: Issues, https://github.com/ai-app-base/bump-version-py/issues
Author: AI App Base
License: ISC
License-File: LICENSE
Requires-Python: >=3.12
Requires-Dist: click>=8.1.0
Requires-Dist: inquirer>=3.1.0
Requires-Dist: packaging>=23.0
Requires-Dist: rich>=13.0.0
Requires-Dist: toml>=0.10.2
